dbine/__init__.py
dbine/cli.py
dbine/connection.py
dbine-0.1.6.dist-info/LICENSE
dbine-0.1.6.dist-info/METADATA
dbine-0.1.6.dist-info/WHEEL
dbine-0.1.6.dist-info/entry_points.txt
dbine-0.1.6.dist-info/top_level.txt
dbine-0.1.6.dist-info/RECORD
