Metadata-Version: 2.1
Name: dbine
Version: 0.1.6
Summary: Auxiliary tools related to databases
Author-email: mskz-3110 <mskz.saito@gmail.com>
Project-URL: Homepage, https://github.com/mskz-3110/dbine
Project-URL: Issues, https://github.com/mskz-3110/dbine/issues
Classifier: Programming Language :: Python :: 3
Classifier: License :: OSI Approved :: MIT License
Classifier: Operating System :: OS Independent
Requires-Python: >=3.13
License-File: LICENSE
Requires-Dist: psycopg
Requires-Dist: mysql-connector-python
Requires-Dist: graspgraph
